{
  "swagger": "2.0",
  "info": {
    "version": "1.0.0",
    "title": "REST API",
    "description": ""
  },
  "host": "localhost:3000",
  "basePath": "/",
  "schemes": [
    "http"
  ],
  "paths": {
    "/api/health": {
      "get": {
        "tags": [
          "Default"
        ],
        "description": "",
        "responses": {
          "default": {
            "description": ""
          }
        }
      }
    },
    "/api/auth/login": {
      "post": {
        "tags": [
          "Auth"
        ],
        "description": "",
        "parameters": [
          {
            "name": "body",
            "in": "body",
            "schema": {
              "type": "object",
              "properties": {
                "email": {
                  "example": "any"
                },
                "password": {
                  "example": "any"
                }
              }
            }
          }
        ],
        "responses": {
          "default": {
            "description": ""
          }
        }
      }
    },
    "/api/auth/refresh-token": {
      "post": {
        "tags": [
          "Auth"
        ],
        "description": "",
        "parameters": [
          {
            "name": "body",
            "in": "body",
            "schema": {
              "type": "object",
              "properties": {
                "refreshToken": {
                  "example": "any"
                }
              }
            }
          }
        ],
        "responses": {
          "default": {
            "description": ""
          }
        }
      }
    },
    "/api/user": {
      "post": {
        "tags": [
          "User"
        ],
        "description": "",
        "parameters": [
          {
            "name": "body",
            "in": "body",
            "schema": {
              "type": "object",
              "properties": {
                "email": {
                  "example": "any"
                },
                "password": {
                  "example": "any"
                },
                "confirmPassword": {
                  "example": "any"
                },
                "name": {
                  "example": "any"
                },
                "gender": {
                  "example": "any"
                }
              }
            }
          }
        ],
        "responses": {
          "default": {
            "description": ""
          }
        }
      }
    },
    "/api/user/admin": {
      "post": {
        "tags": [
          "User"
        ],
        "description": "",
        "parameters": [
          {
            "name": "body",
            "in": "body",
            "schema": {
              "type": "object",
              "properties": {
                "email": {
                  "example": "any"
                },
                "password": {
                  "example": "any"
                },
                "confirmPassword": {
                  "example": "any"
                },
                "name": {
                  "example": "any"
                },
                "roles": {
                  "example": "any"
                },
                "gender": {
                  "example": "any"
                }
              }
            }
          }
        ],
        "responses": {
          "401": {
            "description": "Unauthorized"
          }
        }
      }
    }
  }
}